dash_holoniq_wordcloud/DashWordcloud.py
dash_holoniq_wordcloud/__init__.py
dash_holoniq_wordcloud/_imports_.py
dash_holoniq_wordcloud/dash_holoniq_wordcloud.dev.js
dash_holoniq_wordcloud/dash_holoniq_wordcloud.dev.js.map
dash_holoniq_wordcloud/dash_holoniq_wordcloud.min.js
dash_holoniq_wordcloud/dash_holoniq_wordcloud.min.js.map
dash_holoniq_wordcloud/metadata.json
dash_holoniq_wordcloud/package-info.json
dash_holoniq_wordcloud-0.0.4.dist-info/LICENSE
dash_holoniq_wordcloud-0.0.4.dist-info/METADATA
dash_holoniq_wordcloud-0.0.4.dist-info/WHEEL
dash_holoniq_wordcloud-0.0.4.dist-info/top_level.txt
dash_holoniq_wordcloud-0.0.4.dist-info/RECORD
