Metadata-Version: 2.1
Name: dash_holoniq_wordcloud
Version: 0.0.4
Summary: tag/word cloud, ses the wonderful d3-cloud under the hood
Home-page: https://github.com/stevej2608/dash-holoniq-wordcloud
Author: Steve Jones <jonesst2608@gmail.com>
License: MIT
Platform: UNKNOWN
Classifier: Framework :: Dash
